datapilot/__init__.py
datapilot/__main__.py
datapilot/cli/__init__.py
datapilot/cli/main.py
datapilot/clients/__init__.py
datapilot/clients/altimate/__init__.py
datapilot/clients/altimate/client.py
datapilot/clients/altimate/utils.py
datapilot/config/__init__.py
datapilot/config/config.py
datapilot/config/utils.py
datapilot/core/__init__.py
datapilot/core/insights/__init__.py
datapilot/core/insights/report.py
datapilot/core/insights/schema.py
datapilot/core/insights/utils.py
datapilot/core/insights/base/__init__.py
datapilot/core/insights/base/insight.py
datapilot/core/insights/sql/__init__.py
datapilot/core/insights/sql/base/__init__.py
datapilot/core/insights/sql/base/insight.py
datapilot/core/insights/sql/runtime/__init__.py
datapilot/core/insights/sql/static/__init__.py
datapilot/core/platforms/__init__.py
datapilot/core/platforms/dbt/__init__.py
datapilot/core/platforms/dbt/constants.py
datapilot/core/platforms/dbt/exceptions.py
datapilot/core/platforms/dbt/executor.py
datapilot/core/platforms/dbt/factory.py
datapilot/core/platforms/dbt/formatting.py
datapilot/core/platforms/dbt/utils.py
datapilot/core/platforms/dbt/cli/__init__.py
datapilot/core/platforms/dbt/cli/cli.py
datapilot/core/platforms/dbt/hooks/__init__.py
datapilot/core/platforms/dbt/hooks/executor_hook.py
datapilot/core/platforms/dbt/insights/__init__.py
datapilot/core/platforms/dbt/insights/base.py
datapilot/core/platforms/dbt/insights/schema.py
datapilot/core/platforms/dbt/insights/utils.py
datapilot/core/platforms/dbt/insights/checks/__init__.py
datapilot/core/platforms/dbt/insights/checks/base.py
datapilot/core/platforms/dbt/insights/checks/check_column_desc_are_same.py
datapilot/core/platforms/dbt/insights/checks/check_column_name_contract.py
datapilot/core/platforms/dbt/insights/checks/check_macro_args_have_desc.py
datapilot/core/platforms/dbt/insights/checks/check_macro_has_desc.py
datapilot/core/platforms/dbt/insights/checks/check_model_has_all_columns.py
datapilot_cli-0.0.8.dist-info/AUTHORS.rst
datapilot_cli-0.0.8.dist-info/LICENSE
datapilot_cli-0.0.8.dist-info/METADATA
datapilot_cli-0.0.8.dist-info/WHEEL
datapilot_cli-0.0.8.dist-info/entry_points.txt
datapilot_cli-0.0.8.dist-info/top_level.txt
datapilot_cli-0.0.8.dist-info/RECORD
